focal_loss/__init__.py
focal_loss/focal_loss.py
focal_loss_torch-0.1.2.dist-info/LICENSE
focal_loss_torch-0.1.2.dist-info/METADATA
focal_loss_torch-0.1.2.dist-info/WHEEL
focal_loss_torch-0.1.2.dist-info/top_level.txt
focal_loss_torch-0.1.2.dist-info/RECORD
