Metadata-Version: 2.1
Name: focal-loss-torch
Version: 0.1.2
Summary: Simple pytorch implementation of focal loss
Home-page: https://github.com/mathiaszinnen/focal_loss_torch
Author: Mathias Zinnen
Author-email: mathias.zinnen@gmail.com
License: MIT
Classifier: License :: OSI Approved :: MIT License
Classifier: Programming Language :: Python :: 3
Classifier: Programming Language :: Python :: 3.8
License-File: LICENSE
Requires-Dist: torch
Requires-Dist: numpy
